{"name":"Country","id":"country","data":{"playlists":{"href":"browse\/categories\/country\/playlists?country=US&offset=0&limit=50","items":[{"collaborative":false,"description":"Today's top country hits of the week, worldwide! Cover: Jameson Rodgers","external_urls":{"spotify":"https:\/\/open.spotify.com\/playlist\/37i9dQZF1DX1lVhptIYRda"},"href":"playlists\/37i9dQZF1DX1lVhptIYRda","id":"37i9dQZF1DX1lVhptIYRda","images":[{"height":null,"url":"https:\/\/i.scdn.co\/image\/ab67706f0000000353b6860c675a60849a5122c3","width":null}],"name":"Hot Country","owner":{"display_name":"Spotify","external_urls":{"spotify":"https:\/\/open.spotify.com\/user\/spotify"},"href":"users\/spotify","id":"spotify","type":"user","uri":"spotify:user:spotify"},"primary_color":null,"public":null,"snapshot_id":"MTYzMTg1MTIwMCwwMDAwMDMyODAwMDAwMTdiZjFlOTNlOWUwMDAwMDE3YmYxMWFjYzQ5","tracks":{"href":"playlists\/37i9dQZF1DX1lVhptIYRda\/tracks","total":55},"type":"playlist","uri":"spotify:playlist:37i9dQZF1DX1lVhptIYRda"},{"collaborative":false,"description":"A new shade of Country. Cover: Charley Crockett","external_urls":{"spotify":"https:\/\/open.spotify.com\/playlist\/37i9dQZF1DWUgBy0IJPlHq"},"href":"playlists\/37i9dQZF1DWUgBy0IJPlHq","id":"37i9dQZF1DWUgBy0IJPlHq","images":[{"height":null,"url":"https:\/\/i.scdn.co\/image\/ab67706f00000003848450cf5648de6bb3170679","width":null}],"name":"Indigo","owner":{"display_name":"Spotify","external_urls":{"spotify":"https:\/\/open.spotify.com\/user\/spotify"},"href":"users\/spotify","id":"spotify","type":"user","uri":"spotify:user:spotify"},"primary_color":null,"public":null,"snapshot_id":"MTYzMjA1MzU1NywwMDAwMDAwMGQ0MWQ4Y2Q5OGYwMGIyMDRlOTgwMDk5OGVjZjg0Mjdl","tracks":{"href":"playlists\/37i9dQZF1DWUgBy0IJPlHq\/tracks","total":109},"type":"playlist","uri":"spotify:playlist:37i9dQZF1DWUgBy0IJPlHq"},{"collaborative":false,"description":"New Music Discovery is what we're about.  Try it on for size. Cover: Niko Moon","external_urls":{"spotify":"https:\/\/open.spotify.com\/playlist\/37i9dQZF1DX8S0uQvJ4gaa"},"href":"playlists\/37i9dQZF1DX8S0uQvJ4gaa","id":"37i9dQZF1DX8S0uQvJ4gaa","images":[{"height":null,"url":"https:\/\/i.scdn.co\/image\/ab67706f000000031f401b72e7e5e6bef136dec1","width":null}],"name":"New Boots","owner":{"display_name":"Spotify","external_urls":{"spotify":"https:\/\/open.spotify.com\/user\/spotify"},"href":"users\/spotify","id":"spotify","type":"user","uri":"spotify:user:spotify"},"primary_color":null,"public":null,"snapshot_id":"MTYzMTg1MTIwMCwwMDAwMDI3NTAwMDAwMTdiZjFlOTNlZTUwMDAwMDE3Yjg4MGM2NzRi","tracks":{"href":"playlists\/37i9dQZF1DX8S0uQvJ4gaa\/tracks","total":112},"type":"playlist","uri":"spotify:playlist:37i9dQZF1DX8S0uQvJ4gaa"},{"collaborative":false,"description":"Congratulations to all of the CMA Awards nominees! Watch LIVE from Nashville on Wednesday, Nov. 10 at 8|7c on ABC.","external_urls":{"spotify":"https:\/\/open.spotify.com\/playlist\/37i9dQZF1DX8ZfTXESa5KP"},"href":"playlists\/37i9dQZF1DX8ZfTXESa5KP","id":"37i9dQZF1DX8ZfTXESa5KP","images":[{"height":null,"url":"https:\/\/i.scdn.co\/image\/ab67706f0000000398f36b2c12959a2bab6d8eb9","width":null}],"name":"CMA Awards 2021 Nominees","owner":{"display_name":"Spotify","external_urls":{"spotify":"https:\/\/open.spotify.com\/user\/spotify"},"href":"users\/spotify","id":"spotify","type":"user","uri":"spotify:user:spotify"},"primary_color":null,"public":null,"snapshot_id":"MTYzMTIwNDM1MCwwMDAwMDAyMjAwMDAwMTdiY2I1YjFhMDYwMDAwMDE3YmNhZjlkZjgx","tracks":{"href":"playlists\/37i9dQZF1DX8ZfTXESa5KP\/tracks","total":61},"type":"playlist","uri":"spotify:playlist:37i9dQZF1DX8ZfTXESa5KP"},{"collaborative":false,"description":"Country music to get you back to the basics.","external_urls":{"spotify":"https:\/\/open.spotify.com\/playlist\/37i9dQZF1DWTkxQvqMy4WW"},"href":"playlists\/37i9dQZF1DWTkxQvqMy4WW","id":"37i9dQZF1DWTkxQvqMy4WW","images":[{"height":null,"url":"https:\/\/i.scdn.co\/image\/ab67706f00000003f5b078962d37890234b76125","width":null}],"name":"Chillin' on a Dirt Road","owner":{"display_name":"Spotify","external_urls":{"spotify":"https:\/\/open.spotify.com\/user\/spotify"},"href":"users\/spotify","id":"spotify","type":"user","uri":"spotify:user:spotify"},"primary_color":null,"public":null,"snapshot_id":"MTYzMjA1MzUzOCwwMDAwMDAwMGQ0MWQ4Y2Q5OGYwMGIyMDRlOTgwMDk5OGVjZjg0Mjdl","tracks":{"href":"playlists\/37i9dQZF1DWTkxQvqMy4WW\/tracks","total":80},"type":"playlist","uri":"spotify:playlist:37i9dQZF1DWTkxQvqMy4WW"},{"collaborative":false,"description":"Country that made Country Cool! Cover:  George Strait","external_urls":{"spotify":"https:\/\/open.spotify.com\/playlist\/37i9dQZF1DWVpjAJGB70vU"},"href":"playlists\/37i9dQZF1DWVpjAJGB70vU","id":"37i9dQZF1DWVpjAJGB70vU","images":[{"height":null,"url":"https:\/\/i.scdn.co\/image\/ab67706f000000033c5e9073358df9732d91a30f","width":null}],"name":"90s Country","owner":{"display_name":"Spotify","external_urls":{"spotify":"https:\/\/open.spotify.com\/user\/spotify"},"href":"users\/spotify","id":"spotify","type":"user","uri":"spotify:user:spotify"},"primary_color":null,"public":null,"snapshot_id":"MTYzMTg5MzI1OCwwMDAwMDAzNDAwMDAwMTdiZjQ2YWZmYzYwMDAwMDE3YmY0Njg4YjFm","tracks":{"href":"playlists\/37i9dQZF1DWVpjAJGB70vU\/tracks","total":142},"type":"playlist","uri":"spotify:playlist:37i9dQZF1DWVpjAJGB70vU"},{"collaborative":false,"description":"A decade full of 00s country hits! Cover: Keith Urban, Carrie Underwood, Kenny Chesney","external_urls":{"spotify":"https:\/\/open.spotify.com\/playlist\/37i9dQZF1DXdxUH6sNtcDe"},"href":"playlists\/37i9dQZF1DXdxUH6sNtcDe","id":"37i9dQZF1DXdxUH6sNtcDe","images":[{"height":null,"url":"https:\/\/i.scdn.co\/image\/ab67706f000000030f89886755bdd709f0bd6e10","width":null}],"name":"2000s Country","owner":{"display_name":"Spotify","external_urls":{"spotify":"https:\/\/open.spotify.com\/user\/spotify"},"href":"users\/spotify","id":"spotify","type":"user","uri":"spotify:user:spotify"},"primary_color":null,"public":null,"snapshot_id":"MTYzMjA1MzUyMCwwMDAwMDAwMGQ0MWQ4Y2Q5OGYwMGIyMDRlOTgwMDk5OGVjZjg0Mjdl","tracks":{"href":"playlists\/37i9dQZF1DXdxUH6sNtcDe\/tracks","total":125},"type":"playlist","uri":"spotify:playlist:37i9dQZF1DXdxUH6sNtcDe"},{"collaborative":false,"description":"The perfect soundtrack recipe for a backyard barbecue! ","external_urls":{"spotify":"https:\/\/open.spotify.com\/playlist\/37i9dQZF1DXbIbVYph0Zr5"},"href":"playlists\/37i9dQZF1DXbIbVYph0Zr5","id":"37i9dQZF1DXbIbVYph0Zr5","images":[{"height":null,"url":"https:\/\/i.scdn.co\/image\/ab67706f000000033c5a340bdd0bc167ad56f064","width":null}],"name":"Country Cookout","owner":{"display_name":"Spotify","external_urls":{"spotify":"https:\/\/open.spotify.com\/user\/spotify"},"href":"users\/spotify","id":"spotify","type":"user","uri":"spotify:user:spotify"},"primary_color":null,"public":null,"snapshot_id":"MTYzMjA1MzU1NiwwMDAwMDAwMGQ0MWQ4Y2Q5OGYwMGIyMDRlOTgwMDk5OGVjZjg0Mjdl","tracks":{"href":"playlists\/37i9dQZF1DXbIbVYph0Zr5\/tracks","total":120},"type":"playlist","uri":"spotify:playlist:37i9dQZF1DXbIbVYph0Zr5"},{"collaborative":false,"description":"Spotify Fan Favorites from the last few years.  Artist: Kane Brown","external_urls":{"spotify":"https:\/\/open.spotify.com\/playlist\/37i9dQZF1DWYnwbYQ5HnZU"},"href":"playlists\/37i9dQZF1DWYnwbYQ5HnZU","id":"37i9dQZF1DWYnwbYQ5HnZU","images":[{"height":null,"url":"https:\/\/i.scdn.co\/image\/ab67706f0000000302bfb90d7f7c644607387704","width":null}],"name":"Country Gold","owner":{"display_name":"Spotify","external_urls":{"spotify":"https:\/\/open.spotify.com\/user\/spotify"},"href":"users\/spotify","id":"spotify","type":"user","uri":"spotify:user:spotify"},"primary_color":null,"public":null,"snapshot_id":"MTYzMDQ2ODgwMCwwMDAwMDEwMTAwMDAwMTdiOWY4MzdlOTcwMDAwMDE3YjlkMWU2NDM0","tracks":{"href":"playlists\/37i9dQZF1DWYnwbYQ5HnZU\/tracks","total":86},"type":"playlist","uri":"spotify:playlist:37i9dQZF1DWYnwbYQ5HnZU"},{"collaborative":false,"description":"Need to get your energy level up? This will help!","external_urls":{"spotify":"https:\/\/open.spotify.com\/playlist\/37i9dQZF1DWXLSRKeL7KwM"},"href":"playlists\/37i9dQZF1DWXLSRKeL7KwM","id":"37i9dQZF1DWXLSRKeL7KwM","images":[{"height":null,"url":"https:\/\/i.scdn.co\/image\/ab67706f00000003a46a02f3aaeccdaa10eba231","width":null}],"name":"Energy Booster: Country","owner":{"display_name":"Spotify","external_urls":{"spotify":"https:\/\/open.spotify.com\/user\/spotify"},"href":"users\/spotify","id":"spotify","type":"user","uri":"spotify:user:spotify"},"primary_color":null,"public":null,"snapshot_id":"MTYzMjA1MzUxMCwwMDAwMDAwMGQ0MWQ4Y2Q5OGYwMGIyMDRlOTgwMDk5OGVjZjg0Mjdl","tracks":{"href":"playlists\/37i9dQZF1DWXLSRKeL7KwM\/tracks","total":150},"type":"playlist","uri":"spotify:playlist:37i9dQZF1DWXLSRKeL7KwM"},{"collaborative":false,"description":"The perfect soundtrack for a day on the water. ","external_urls":{"spotify":"https:\/\/open.spotify.com\/playlist\/37i9dQZF1DXcSzYlwgjiSi"},"href":"playlists\/37i9dQZF1DXcSzYlwgjiSi","id":"37i9dQZF1DXcSzYlwgjiSi","images":[{"height":null,"url":"https:\/\/i.scdn.co\/image\/ab67706f000000031ce469c867c1c6e1cc7f815b","width":null}],"name":"Party Cove","owner":{"display_name":"Spotify","external_urls":{"spotify":"https:\/\/open.spotify.com\/user\/spotify"},"href":"users\/spotify","id":"spotify","type":"user","uri":"spotify:user:spotify"},"primary_color":null,"public":null,"snapshot_id":"MTYzMDY0MTcyMCwwMDAwMDAxYzAwMDAwMTdiYTlkMjBiMWEwMDAwMDE3MmUxYzkwZWJi","tracks":{"href":"playlists\/37i9dQZF1DXcSzYlwgjiSi\/tracks","total":116},"type":"playlist","uri":"spotify:playlist:37i9dQZF1DXcSzYlwgjiSi"},{"collaborative":false,"description":"The most memorable country hits from the 2010's. Cover: Miranda Lambert, Luke Bryan and Jason Aldean.","external_urls":{"spotify":"https:\/\/open.spotify.com\/playlist\/37i9dQZF1DWXdiK4WAVRUW"},"href":"playlists\/37i9dQZF1DWXdiK4WAVRUW","id":"37i9dQZF1DWXdiK4WAVRUW","images":[{"height":null,"url":"https:\/\/i.scdn.co\/image\/ab67706f00000003e5a3bb0260aaf546544ca88b","width":null}],"name":"2010s Country","owner":{"display_name":"Spotify","external_urls":{"spotify":"https:\/\/open.spotify.com\/user\/spotify"},"href":"users\/spotify","id":"spotify","type":"user","uri":"spotify:user:spotify"},"primary_color":null,"public":null,"snapshot_id":"MTYzMjA1MzUxNCwwMDAwMDAwMGQ0MWQ4Y2Q5OGYwMGIyMDRlOTgwMDk5OGVjZjg0Mjdl","tracks":{"href":"playlists\/37i9dQZF1DWXdiK4WAVRUW\/tracks","total":200},"type":"playlist","uri":"spotify:playlist:37i9dQZF1DWXdiK4WAVRUW"},{"collaborative":false,"description":"Country's Top 50 most played songs\u2014in the world. Updated weekly. Formerly Nashville's Worldwide Hot 50.","external_urls":{"spotify":"https:\/\/open.spotify.com\/playlist\/37i9dQZF1DX7aUUBCKwo4Y"},"href":"playlists\/37i9dQZF1DX7aUUBCKwo4Y","id":"37i9dQZF1DX7aUUBCKwo4Y","images":[{"height":null,"url":"https:\/\/i.scdn.co\/image\/ab67706f000000030fb6fbf815c9b2586773f942","width":null}],"name":"Country Worldwide Hot 50","owner":{"display_name":"Spotify","external_urls":{"spotify":"https:\/\/open.spotify.com\/user\/spotify"},"href":"users\/spotify","id":"spotify","type":"user","uri":"spotify:user:spotify"},"primary_color":null,"public":null,"snapshot_id":"MTYzMTY3ODQwMCwwMDAwMDBiYzAwMDAwMTdiZTc5Yzg2NzAwMDAwMDE3YWM5ODU5NTg0","tracks":{"href":"playlists\/37i9dQZF1DX7aUUBCKwo4Y\/tracks","total":50},"type":"playlist","uri":"spotify:playlist:37i9dQZF1DX7aUUBCKwo4Y"},{"collaborative":false,"description":"Nothing but beautiful country love songs. ","external_urls":{"spotify":"https:\/\/open.spotify.com\/playlist\/37i9dQZF1DX8WMG8VPSOJC"},"href":"playlists\/37i9dQZF1DX8WMG8VPSOJC","id":"37i9dQZF1DX8WMG8VPSOJC","images":[{"height":null,"url":"https:\/\/i.scdn.co\/image\/ab67706f000000031416f67f937b9ee33b3753e2","width":null}],"name":"Country Kind of Love","owner":{"display_name":"Spotify","external_urls":{"spotify":"https:\/\/open.spotify.com\/user\/spotify"},"href":"users\/spotify","id":"spotify","type":"user","uri":"spotify:user:spotify"},"primary_color":null,"public":null,"snapshot_id":"MTYzMjA1MzUzOSwwMDAwMDAwMGQ0MWQ4Y2Q5OGYwMGIyMDRlOTgwMDk5OGVjZjg0Mjdl","tracks":{"href":"playlists\/37i9dQZF1DX8WMG8VPSOJC\/tracks","total":85},"type":"playlist","uri":"spotify:playlist:37i9dQZF1DX8WMG8VPSOJC"},{"collaborative":false,"description":"The top country hits of the week across America! Cover: Lainey Wilson\n","external_urls":{"spotify":"https:\/\/open.spotify.com\/playlist\/37i9dQZF1DXaJXCbmtHVHV"},"href":"playlists\/37i9dQZF1DXaJXCbmtHVHV","id":"37i9dQZF1DXaJXCbmtHVHV","images":[{"height":null,"url":"https:\/\/i.scdn.co\/image\/ab67706f00000003637634d7c634ecee243021f9","width":null}],"name":"Big Country","owner":{"display_name":"Spotify","external_urls":{"spotify":"https:\/\/open.spotify.com\/user\/spotify"},"href":"users\/spotify","id":"spotify","type":"user","uri":"spotify:user:spotify"},"primary_color":null,"public":null,"snapshot_id":"MTYzMTU1OTE2MSwwMDAwMDA4ZDAwMDAwMTdiZTA4MTE2OWIwMDAwMDE3YjlkY2UxN2Ri","tracks":{"href":"playlists\/37i9dQZF1DXaJXCbmtHVHV\/tracks","total":50},"type":"playlist","uri":"spotify:playlist:37i9dQZF1DXaJXCbmtHVHV"},{"collaborative":false,"description":"A fun library of country hits to pass on to the next generation!","external_urls":{"spotify":"https:\/\/open.spotify.com\/playlist\/37i9dQZF1DWVFzWmxRnRJH"},"href":"playlists\/37i9dQZF1DWVFzWmxRnRJH","id":"37i9dQZF1DWVFzWmxRnRJH","images":[{"height":null,"url":"https:\/\/i.scdn.co\/image\/ab67706f00000003bd9929112e8499738fa598cf","width":null}],"name":"Raised on Country","owner":{"display_name":"Spotify","external_urls":{"spotify":"https:\/\/open.spotify.com\/user\/spotify"},"href":"users\/spotify","id":"spotify","type":"user","uri":"spotify:user:spotify"},"primary_color":null,"public":null,"snapshot_id":"MTYzMjA1MzUxNiwwMDAwMDAwMGQ0MWQ4Y2Q5OGYwMGIyMDRlOTgwMDk5OGVjZjg0Mjdl","tracks":{"href":"playlists\/37i9dQZF1DWVFzWmxRnRJH\/tracks","total":100},"type":"playlist","uri":"spotify:playlist:37i9dQZF1DWVFzWmxRnRJH"},{"collaborative":false,"description":"The decade when New Traditional artists like George Strait, Reba McEntire, and Randy Travis dominated the Country scene.","external_urls":{"spotify":"https:\/\/open.spotify.com\/playlist\/37i9dQZF1DX6RCydf9ytsj"},"href":"playlists\/37i9dQZF1DX6RCydf9ytsj","id":"37i9dQZF1DX6RCydf9ytsj","images":[{"height":null,"url":"https:\/\/i.scdn.co\/image\/ab67706f0000000397ccc4082777009c87e97202","width":null}],"name":"80s Country","owner":{"display_name":"Spotify","external_urls":{"spotify":"https:\/\/open.spotify.com\/user\/spotify"},"href":"users\/spotify","id":"spotify","type":"user","uri":"spotify:user:spotify"},"primary_color":null,"public":null,"snapshot_id":"MTYzMjA1MzU2MCwwMDAwMDAwMGQ0MWQ4Y2Q5OGYwMGIyMDRlOTgwMDk5OGVjZjg0Mjdl","tracks":{"href":"playlists\/37i9dQZF1DX6RCydf9ytsj\/tracks","total":163},"type":"playlist","uri":"spotify:playlist:37i9dQZF1DX6RCydf9ytsj"},{"collaborative":false,"description":"Recent tracks from the Hot Country playlist that are still smokin'.  Cover: Sam Hunt","external_urls":{"spotify":"https:\/\/open.spotify.com\/playlist\/37i9dQZF1DX6rVyqO2FaN8"},"href":"playlists\/37i9dQZF1DX6rVyqO2FaN8","id":"37i9dQZF1DX6rVyqO2FaN8","images":[{"height":null,"url":"https:\/\/i.scdn.co\/image\/ab67706f000000034ce5a830cc3a21961f3f878c","width":null}],"name":"Still Hot","owner":{"display_name":"Spotify","external_urls":{"spotify":"https:\/\/open.spotify.com\/user\/spotify"},"href":"users\/spotify","id":"spotify","type":"user","uri":"spotify:user:spotify"},"primary_color":null,"public":null,"snapshot_id":"MTYzMTg1MTIwMCwwMDAwMDA4NjAwMDAwMTdiZjFlOTNlYTIwMDAwMDE3YjlkYjk5NmRk","tracks":{"href":"playlists\/37i9dQZF1DX6rVyqO2FaN8\/tracks","total":64},"type":"playlist","uri":"spotify:playlist:37i9dQZF1DX6rVyqO2FaN8"},{"collaborative":false,"description":"A compilation of the all-time biggest hits in Country Music.","external_urls":{"spotify":"https:\/\/open.spotify.com\/playlist\/37i9dQZF1DWZBCPUIUs2iR"},"href":"playlists\/37i9dQZF1DWZBCPUIUs2iR","id":"37i9dQZF1DWZBCPUIUs2iR","images":[{"height":null,"url":"https:\/\/i.scdn.co\/image\/ab67706f0000000321252477d94bc3cffbbb189f","width":null}],"name":"Country's Greatest Hits","owner":{"display_name":"Spotify","external_urls":{"spotify":"https:\/\/open.spotify.com\/user\/spotify"},"href":"users\/spotify","id":"spotify","type":"user","uri":"spotify:user:spotify"},"primary_color":null,"public":null,"snapshot_id":"MTYxODk3NDE0OCwwMDAwMDAwODAwMDAwMTc4ZjI2MTA4NzAwMDAwMDE3OGYyNjA5ZmNh","tracks":{"href":"playlists\/37i9dQZF1DWZBCPUIUs2iR\/tracks","total":99},"type":"playlist","uri":"spotify:playlist:37i9dQZF1DWZBCPUIUs2iR"},{"collaborative":false,"description":"Country Music that ROCKS!!  \nCover:  Koe Wetzel","external_urls":{"spotify":"https:\/\/open.spotify.com\/playlist\/37i9dQZF1DWWH0izG4erma"},"href":"playlists\/37i9dQZF1DWWH0izG4erma","id":"37i9dQZF1DWWH0izG4erma","images":[{"height":null,"url":"https:\/\/i.scdn.co\/image\/ab67706f00000003ea96a99dda21e4f19b2041ca","width":null}],"name":"Country Rocks","owner":{"display_name":"Spotify","external_urls":{"spotify":"https:\/\/open.spotify.com\/user\/spotify"},"href":"users\/spotify","id":"spotify","type":"user","uri":"spotify:user:spotify"},"primary_color":null,"public":null,"snapshot_id":"MTYzMTg1MTI2MCwwMDAwMDA5NTAwMDAwMTdiZjFlYTI4ZDgwMDAwMDE3YjlkMjJlNzE3","tracks":{"href":"playlists\/37i9dQZF1DWWH0izG4erma\/tracks","total":113},"type":"playlist","uri":"spotify:playlist:37i9dQZF1DWWH0izG4erma"},{"collaborative":false,"description":"The right music can make a good tailgate great.","external_urls":{"spotify":"https:\/\/open.spotify.com\/playlist\/37i9dQZF1DXdgnLr18vPvu"},"href":"playlists\/37i9dQZF1DXdgnLr18vPvu","id":"37i9dQZF1DXdgnLr18vPvu","images":[{"height":null,"url":"https:\/\/i.scdn.co\/image\/ab67706f000000039aee8ba760717423d701f2ff","width":null}],"name":"Tailgate Party","owner":{"display_name":"Spotify","external_urls":{"spotify":"https:\/\/open.spotify.com\/user\/spotify"},"href":"users\/spotify","id":"spotify","type":"user","uri":"spotify:user:spotify"},"primary_color":null,"public":null,"snapshot_id":"MTYzMDUyNzgzMiwwMDAwMDA0OTAwMDAwMTdiYTMwODQxNGUwMDAwMDE3YmEyZmFmNWQx","tracks":{"href":"playlists\/37i9dQZF1DXdgnLr18vPvu\/tracks","total":93},"type":"playlist","uri":"spotify:playlist:37i9dQZF1DXdgnLr18vPvu"},{"collaborative":false,"description":"Top trending new and recent tracks from the last few weeks.  Cover: Mickey Guyton","external_urls":{"spotify":"https:\/\/open.spotify.com\/playlist\/37i9dQZF1DWW7RgkOJG32Y"},"href":"playlists\/37i9dQZF1DWW7RgkOJG32Y","id":"37i9dQZF1DWW7RgkOJG32Y","images":[{"height":null,"url":"https:\/\/i.scdn.co\/image\/ab67706f0000000308fcd6257427242dd8b52d29","width":null}],"name":"Breakout Country","owner":{"display_name":"Spotify","external_urls":{"spotify":"https:\/\/open.spotify.com\/user\/spotify"},"href":"users\/spotify","id":"spotify","type":"user","uri":"spotify:user:spotify"},"primary_color":null,"public":null,"snapshot_id":"MTYzMTg1MTIwMCwwMDAwMDFmMTAwMDAwMTdiZjFlOTNlYmMwMDAwMDE3YjlkYWFmNjY2","tracks":{"href":"playlists\/37i9dQZF1DWW7RgkOJG32Y\/tracks","total":85},"type":"playlist","uri":"spotify:playlist:37i9dQZF1DWW7RgkOJG32Y"},{"collaborative":false,"description":"From the Dance Halls and Honky Tonks across America to the World! Formerly Texas Music Now. Cover: Cody Johnson","external_urls":{"spotify":"https:\/\/open.spotify.com\/playlist\/37i9dQZF1DX3Ee0ngF5ZVQ"},"href":"playlists\/37i9dQZF1DX3Ee0ngF5ZVQ","id":"37i9dQZF1DX3Ee0ngF5ZVQ","images":[{"height":null,"url":"https:\/\/i.scdn.co\/image\/ab67706f000000037a70d835d717e657be7829fb","width":null}],"name":"Texas Country Now","owner":{"display_name":"Spotify","external_urls":{"spotify":"https:\/\/open.spotify.com\/user\/spotify"},"href":"users\/spotify","id":"spotify","type":"user","uri":"spotify:user:spotify"},"primary_color":null,"public":null,"snapshot_id":"MTYzMTg1MTIwMCwwMDAwMDBkZTAwMDAwMTdiZjFlOTNlYjgwMDAwMDE3YjlkZDc3NDgx","tracks":{"href":"playlists\/37i9dQZF1DX3Ee0ngF5ZVQ\/tracks","total":122},"type":"playlist","uri":"spotify:playlist:37i9dQZF1DX3Ee0ngF5ZVQ"},{"collaborative":false,"description":"The extraordinary women making great country music today.  Cover: Runaway June","external_urls":{"spotify":"https:\/\/open.spotify.com\/playlist\/37i9dQZF1DX49poIUZYXp7"},"href":"playlists\/37i9dQZF1DX49poIUZYXp7","id":"37i9dQZF1DX49poIUZYXp7","images":[{"height":null,"url":"https:\/\/i.scdn.co\/image\/ab67706f000000030daa35edd51c4eb4510d48ff","width":null}],"name":"Women of Country","owner":{"display_name":"Spotify","external_urls":{"spotify":"https:\/\/open.spotify.com\/user\/spotify"},"href":"users\/spotify","id":"spotify","type":"user","uri":"spotify:user:spotify"},"primary_color":null,"public":null,"snapshot_id":"MTYzMjA1MzUxNiwwMDAwMDAwMGQ0MWQ4Y2Q5OGYwMGIyMDRlOTgwMDk5OGVjZjg0Mjdl","tracks":{"href":"playlists\/37i9dQZF1DX49poIUZYXp7\/tracks","total":100},"type":"playlist","uri":"spotify:playlist:37i9dQZF1DX49poIUZYXp7"},{"collaborative":false,"description":"The Country Coffeehouse is open! Grab a cup and lean back to some low-key country.","external_urls":{"spotify":"https:\/\/open.spotify.com\/playlist\/37i9dQZF1DWYiR2Uqcon0X"},"href":"playlists\/37i9dQZF1DWYiR2Uqcon0X","id":"37i9dQZF1DWYiR2Uqcon0X","images":[{"height":null,"url":"https:\/\/i.scdn.co\/image\/ab67706f000000031c853be1a053c7a3a24d69db","width":null}],"name":"Country Coffeehouse","owner":{"display_name":"Spotify","external_urls":{"spotify":"https:\/\/open.spotify.com\/user\/spotify"},"href":"users\/spotify","id":"spotify","type":"user","uri":"spotify:user:spotify"},"primary_color":null,"public":null,"snapshot_id":"MTYzMjA1MzUzMywwMDAwMDAwMGQ0MWQ4Y2Q5OGYwMGIyMDRlOTgwMDk5OGVjZjg0Mjdl","tracks":{"href":"playlists\/37i9dQZF1DWYiR2Uqcon0X\/tracks","total":83},"type":"playlist","uri":"spotify:playlist:37i9dQZF1DWYiR2Uqcon0X"},{"collaborative":false,"description":"The biggest Texas Music Hits over the last couple of years.","external_urls":{"spotify":"https:\/\/open.spotify.com\/playlist\/37i9dQZF1DX7M1twJ8D6TS"},"href":"playlists\/37i9dQZF1DX7M1twJ8D6TS","id":"37i9dQZF1DX7M1twJ8D6TS","images":[{"height":null,"url":"https:\/\/i.scdn.co\/image\/ab67706f00000003f57a13a556077b45a5f7e381","width":null}],"name":"Texas Music Rewind","owner":{"display_name":"Spotify","external_urls":{"spotify":"https:\/\/open.spotify.com\/user\/spotify"},"href":"users\/spotify","id":"spotify","type":"user","uri":"spotify:user:spotify"},"primary_color":null,"public":null,"snapshot_id":"MTYzMDY0MTY2MCwwMDAwMDAxZjAwMDAwMTdiYTlkMTIwYzkwMDAwMDE3MzBhY2ZiOGEy","tracks":{"href":"playlists\/37i9dQZF1DX7M1twJ8D6TS\/tracks","total":106},"type":"playlist","uri":"spotify:playlist:37i9dQZF1DX7M1twJ8D6TS"},{"collaborative":false,"description":"The cream of today's Country crop. Cover: Southbound","external_urls":{"spotify":"https:\/\/open.spotify.com\/playlist\/37i9dQZF1DWXepGEFFmQXJ"},"href":"playlists\/37i9dQZF1DWXepGEFFmQXJ","id":"37i9dQZF1DWXepGEFFmQXJ","images":[{"height":null,"url":"https:\/\/i.scdn.co\/image\/ab67706f0000000341a13e074a33ff292cbafeeb","width":null}],"name":"Fresh Country","owner":{"display_name":"Spotify","external_urls":{"spotify":"https:\/\/open.spotify.com\/user\/spotify"},"href":"users\/spotify","id":"spotify","type":"user","uri":"spotify:user:spotify"},"primary_color":null,"public":null,"snapshot_id":"MTYzMTgwMDgwMCwwMDAwMDFiMzAwMDAwMTdiZWVlODMzODMwMDAwMDE3YmRkZGZiZDZi","tracks":{"href":"playlists\/37i9dQZF1DWXepGEFFmQXJ\/tracks","total":60},"type":"playlist","uri":"spotify:playlist:37i9dQZF1DWXepGEFFmQXJ"},{"collaborative":false,"description":"Country gone wild! You never know what you're gonna get.  Artist: Kacey Musgraves","external_urls":{"spotify":"https:\/\/open.spotify.com\/playlist\/37i9dQZF1DX5mB2C8gBeUM"},"href":"playlists\/37i9dQZF1DX5mB2C8gBeUM","id":"37i9dQZF1DX5mB2C8gBeUM","images":[{"height":null,"url":"https:\/\/i.scdn.co\/image\/ab67706f00000003eace7306d50e22175abada36","width":null}],"name":"Wild Country","owner":{"display_name":"Spotify","external_urls":{"spotify":"https:\/\/open.spotify.com\/user\/spotify"},"href":"users\/spotify","id":"spotify","type":"user","uri":"spotify:user:spotify"},"primary_color":null,"public":null,"snapshot_id":"MTYzMTg1MTI2MCwwMDAwMDM0NzAwMDAwMTdiZjFlYTI4YzQwMDAwMDE3YmM1ZWRhYjU1","tracks":{"href":"playlists\/37i9dQZF1DX5mB2C8gBeUM\/tracks","total":146},"type":"playlist","uri":"spotify:playlist:37i9dQZF1DX5mB2C8gBeUM"},{"collaborative":false,"description":"The early pioneers and current favorites in Southern Rock.  Cover:  The Godfather...Charlie Daniels.","external_urls":{"spotify":"https:\/\/open.spotify.com\/playlist\/37i9dQZF1DXbDjX0hus3Iu"},"href":"playlists\/37i9dQZF1DXbDjX0hus3Iu","id":"37i9dQZF1DXbDjX0hus3Iu","images":[{"height":null,"url":"https:\/\/i.scdn.co\/image\/ab67706f0000000305b5a859cc923f25788cc627","width":null}],"name":"Southern Rock 101","owner":{"display_name":"Spotify","external_urls":{"spotify":"https:\/\/open.spotify.com\/user\/spotify"},"href":"users\/spotify","id":"spotify","type":"user","uri":"spotify:user:spotify"},"primary_color":null,"public":null,"snapshot_id":"MTYwNDQzMDA3MiwwMDAwMDAyYjAwMDAwMTc1OGY3YzA5ODIwMDAwMDE2ZDE1MmZiOTYz","tracks":{"href":"playlists\/37i9dQZF1DXbDjX0hus3Iu\/tracks","total":106},"type":"playlist","uri":"spotify:playlist:37i9dQZF1DXbDjX0hus3Iu"},{"collaborative":false,"description":"Sweat it out with your favorite country workout songs.","external_urls":{"spotify":"https:\/\/open.spotify.com\/playlist\/37i9dQZF1DX5OrO2Jxuvdn"},"href":"playlists\/37i9dQZF1DX5OrO2Jxuvdn","id":"37i9dQZF1DX5OrO2Jxuvdn","images":[{"height":null,"url":"https:\/\/i.scdn.co\/image\/ab67706f00000003c50bf74f8153ee7cef3b0f67","width":null}],"name":"Country Workout","owner":{"display_name":"Spotify","external_urls":{"spotify":"https:\/\/open.spotify.com\/user\/spotify"},"href":"users\/spotify","id":"spotify","type":"user","uri":"spotify:user:spotify"},"primary_color":null,"public":null,"snapshot_id":"MTYzMjA1MzUzNiwwMDAwMDAwMGQ0MWQ4Y2Q5OGYwMGIyMDRlOTgwMDk5OGVjZjg0Mjdl","tracks":{"href":"playlists\/37i9dQZF1DX5OrO2Jxuvdn\/tracks","total":100},"type":"playlist","uri":"spotify:playlist:37i9dQZF1DX5OrO2Jxuvdn"},{"collaborative":false,"description":"All of the newest country music releases in one playlist!","external_urls":{"spotify":"https:\/\/open.spotify.com\/playlist\/37i9dQZF1DWVn8zvR5ROMB"},"href":"playlists\/37i9dQZF1DWVn8zvR5ROMB","id":"37i9dQZF1DWVn8zvR5ROMB","images":[{"height":null,"url":"https:\/\/i.scdn.co\/image\/ab67706f00000003c99c13fa7633e6d28653c2f3","width":null}],"name":"New Music Nashville","owner":{"display_name":"Spotify","external_urls":{"spotify":"https:\/\/open.spotify.com\/user\/spotify"},"href":"users\/spotify","id":"spotify","type":"user","uri":"spotify:user:spotify"},"primary_color":null,"public":null,"snapshot_id":"MTYzMTg1MTI2MCwwMDAwMDEzZDAwMDAwMTdiZjFlYTI4ZGYwMDAwMDE3MGFmM2Y0NTdl","tracks":{"href":"playlists\/37i9dQZF1DWVn8zvR5ROMB\/tracks","total":127},"type":"playlist","uri":"spotify:playlist:37i9dQZF1DWVn8zvR5ROMB"},{"collaborative":false,"description":"Many would say that this decade is a \"Golden Era\" for country music.","external_urls":{"spotify":"https:\/\/open.spotify.com\/playlist\/37i9dQZF1DX7CGYgLhqwu5"},"href":"playlists\/37i9dQZF1DX7CGYgLhqwu5","id":"37i9dQZF1DX7CGYgLhqwu5","images":[{"height":null,"url":"https:\/\/i.scdn.co\/image\/ab67706f000000034bbe3cef3e5b5a51a30629ee","width":null}],"name":"60s Country","owner":{"display_name":"Spotify","external_urls":{"spotify":"https:\/\/open.spotify.com\/user\/spotify"},"href":"users\/spotify","id":"spotify","type":"user","uri":"spotify:user:spotify"},"primary_color":null,"public":null,"snapshot_id":"MTYzMjA1MzUxMCwwMDAwMDAwMGQ0MWQ4Y2Q5OGYwMGIyMDRlOTgwMDk5OGVjZjg0Mjdl","tracks":{"href":"playlists\/37i9dQZF1DX7CGYgLhqwu5\/tracks","total":102},"type":"playlist","uri":"spotify:playlist:37i9dQZF1DX7CGYgLhqwu5"},{"collaborative":false,"description":"A complete playlist of all the winners & nominees. Tune in to the ACM Awards LIVE on CBS & Paramount + on April 18th 8\/7c!","external_urls":{"spotify":"https:\/\/open.spotify.com\/playlist\/37i9dQZF1DX13kFuGnInkY"},"href":"playlists\/37i9dQZF1DX13kFuGnInkY","id":"37i9dQZF1DX13kFuGnInkY","images":[{"height":null,"url":"https:\/\/i.scdn.co\/image\/ab67706f000000035a4adb61b0551b8c58231e0c","width":null}],"name":"ACM Awards 2021","owner":{"display_name":"Spotify","external_urls":{"spotify":"https:\/\/open.spotify.com\/user\/spotify"},"href":"users\/spotify","id":"spotify","type":"user","uri":"spotify:user:spotify"},"primary_color":null,"public":null,"snapshot_id":"MTYxODc4Mjk1MiwwMDAwMDAwZjAwMDAwMTc4ZTZmYjlkMzMwMDAwMDE3ODIxZTMyZmM3","tracks":{"href":"playlists\/37i9dQZF1DX13kFuGnInkY\/tracks","total":102},"type":"playlist","uri":"spotify:playlist:37i9dQZF1DX13kFuGnInkY"},{"collaborative":false,"description":"Unique versions of hit songs by other artists.  Cover:  Trisha Yearwood and Garth Brooks.","external_urls":{"spotify":"https:\/\/open.spotify.com\/playlist\/37i9dQZF1DX1KHLbhJkg7B"},"href":"playlists\/37i9dQZF1DX1KHLbhJkg7B","id":"37i9dQZF1DX1KHLbhJkg7B","images":[{"height":null,"url":"https:\/\/i.scdn.co\/image\/ab67706f000000037daabf4cb2d58da1b130d3e0","width":null}],"name":"Country Covers","owner":{"display_name":"Spotify","external_urls":{"spotify":"https:\/\/open.spotify.com\/user\/spotify"},"href":"users\/spotify","id":"spotify","type":"user","uri":"spotify:user:spotify"},"primary_color":null,"public":null,"snapshot_id":"MTYzMjA1MzUyMiwwMDAwMDAwMGQ0MWQ4Y2Q5OGYwMGIyMDRlOTgwMDk5OGVjZjg0Mjdl","tracks":{"href":"playlists\/37i9dQZF1DX1KHLbhJkg7B\/tracks","total":100},"type":"playlist","uri":"spotify:playlist:37i9dQZF1DX1KHLbhJkg7B"},{"collaborative":false,"description":"Music City must-hears. Cover: Sam Grow","external_urls":{"spotify":"https:\/\/open.spotify.com\/playlist\/37i9dQZF1DX0bUGQdz5BJG"},"href":"playlists\/37i9dQZF1DX0bUGQdz5BJG","id":"37i9dQZF1DX0bUGQdz5BJG","images":[{"height":null,"url":"https:\/\/i.scdn.co\/image\/ab67706f00000003b79ade50686fc552b6a3f2c6","width":null}],"name":"Next From Nashville","owner":{"display_name":"Spotify","external_urls":{"spotify":"https:\/\/open.spotify.com\/user\/spotify"},"href":"users\/spotify","id":"spotify","type":"user","uri":"spotify:user:spotify"},"primary_color":null,"public":null,"snapshot_id":"MTYzMTg1MTI2MCwwMDAwMDI5NzAwMDAwMTdiZjFlYTI4ZjIwMDAwMDE3YmYwNTRiYzY5","tracks":{"href":"playlists\/37i9dQZF1DX0bUGQdz5BJG\/tracks","total":137},"type":"playlist","uri":"spotify:playlist:37i9dQZF1DX0bUGQdz5BJG"},{"collaborative":false,"description":"Miranda Lambert, Jon Randall and Jack Ingram takeover in celebration of the new album, \"The Marfa Tapes,\" out May 7th.","external_urls":{"spotify":"https:\/\/open.spotify.com\/playlist\/37i9dQZF1DX05oRSrPGj3d"},"href":"playlists\/37i9dQZF1DX05oRSrPGj3d","id":"37i9dQZF1DX05oRSrPGj3d","images":[{"height":null,"url":"https:\/\/i.scdn.co\/image\/ab67706f0000000381ad6f5133321050d82f6c88","width":null}],"name":"Heart Of Texas","owner":{"display_name":"Spotify","external_urls":{"spotify":"https:\/\/open.spotify.com\/user\/spotify"},"href":"users\/spotify","id":"spotify","type":"user","uri":"spotify:user:spotify"},"primary_color":null,"public":null,"snapshot_id":"MTYyMDM2MDA2MCwwMDAwMDAwNjAwMDAwMTc5NDRmYzVjZDUwMDAwMDE3N2ZmNjZjZWQ4","tracks":{"href":"playlists\/37i9dQZF1DX05oRSrPGj3d\/tracks","total":52},"type":"playlist","uri":"spotify:playlist:37i9dQZF1DX05oRSrPGj3d"},{"collaborative":false,"description":"The country way of testifying. \nCover: Larry Fleet","external_urls":{"spotify":"https:\/\/open.spotify.com\/playlist\/37i9dQZF1DWU2LcZVHsTdv"},"href":"playlists\/37i9dQZF1DWU2LcZVHsTdv","id":"37i9dQZF1DWU2LcZVHsTdv","images":[{"height":null,"url":"https:\/\/i.scdn.co\/image\/ab67706f00000003f0382155f084b0a144511017","width":null}],"name":"Country by the Grace of God","owner":{"display_name":"Spotify","external_urls":{"spotify":"https:\/\/open.spotify.com\/user\/spotify"},"href":"users\/spotify","id":"spotify","type":"user","uri":"spotify:user:spotify"},"primary_color":null,"public":null,"snapshot_id":"MTYzMTg1MTIwMCwwMDAwMDA3YzAwMDAwMTdiZjFlOTNlYTgwMDAwMDE3YjlkZGNlMzQ5","tracks":{"href":"playlists\/37i9dQZF1DWU2LcZVHsTdv\/tracks","total":81},"type":"playlist","uri":"spotify:playlist:37i9dQZF1DWU2LcZVHsTdv"},{"collaborative":false,"description":"The powerful women of country. Cover: Dolly Parton #SpotifyTBT","external_urls":{"spotify":"https:\/\/open.spotify.com\/playlist\/37i9dQZF1DWTQrwBpetTXv"},"href":"playlists\/37i9dQZF1DWTQrwBpetTXv","id":"37i9dQZF1DWTQrwBpetTXv","images":[{"height":null,"url":"https:\/\/i.scdn.co\/image\/ab67706f000000031535c0f972586083905e010d","width":null}],"name":"#SpotifyTBT: Women of Country","owner":{"display_name":"Spotify","external_urls":{"spotify":"https:\/\/open.spotify.com\/user\/spotify"},"href":"users\/spotify","id":"spotify","type":"user","uri":"spotify:user:spotify"},"primary_color":null,"public":null,"snapshot_id":"MTU5MzM5NTkzOSwwMDAwMDAwNDAwMDAwMTcyZmRjYzg4ZDEwMDAwMDE3MGVmZTQxZTc4","tracks":{"href":"playlists\/37i9dQZF1DWTQrwBpetTXv\/tracks","total":70},"type":"playlist","uri":"spotify:playlist:37i9dQZF1DWTQrwBpetTXv"},{"collaborative":false,"description":"Country Music Association award-winning and nominated music from artists then, now, and forever.","external_urls":{"spotify":"https:\/\/open.spotify.com\/playlist\/37i9dQZF1DX9hWdQ46pHPo"},"href":"playlists\/37i9dQZF1DX9hWdQ46pHPo","id":"37i9dQZF1DX9hWdQ46pHPo","images":[{"height":null,"url":"https:\/\/i.scdn.co\/image\/ab67706f0000000332997c49812a329dfcecbf4b","width":null}],"name":"Forever Country","owner":{"display_name":"Spotify","external_urls":{"spotify":"https:\/\/open.spotify.com\/user\/spotify"},"href":"users\/spotify","id":"spotify","type":"user","uri":"spotify:user:spotify"},"primary_color":null,"public":null,"snapshot_id":"MTYwMzQ3OTcyMCwwMDAwMDM5ZDAwMDAwMTc1NTZkNmQxZTEwMDAwMDE2ZDAwYjI0ZWQw","tracks":{"href":"playlists\/37i9dQZF1DX9hWdQ46pHPo\/tracks","total":78},"type":"playlist","uri":"spotify:playlist:37i9dQZF1DX9hWdQ46pHPo"},{"collaborative":false,"description":"Fresh country music by independent artists every Wednesday. Cover: Alana Springsteen","external_urls":{"spotify":"https:\/\/open.spotify.com\/playlist\/37i9dQZF1DWYUfsq4hxHWP"},"href":"playlists\/37i9dQZF1DWYUfsq4hxHWP","id":"37i9dQZF1DWYUfsq4hxHWP","images":[{"height":null,"url":"https:\/\/i.scdn.co\/image\/ab67706f000000031aef946d63a7a9249ba552d2","width":null}],"name":"Fresh Finds: Country","owner":{"display_name":"Spotify","external_urls":{"spotify":"https:\/\/open.spotify.com\/user\/spotify"},"href":"users\/spotify","id":"spotify","type":"user","uri":"spotify:user:spotify"},"primary_color":null,"public":null,"snapshot_id":"MTYzMTY3ODQwMCwwMDAwMDE3ZjAwMDAwMTdiZTc5Yzg2N2YwMDAwMDE3Yjk4YzAwOTAz","tracks":{"href":"playlists\/37i9dQZF1DWYUfsq4hxHWP\/tracks","total":154},"type":"playlist","uri":"spotify:playlist:37i9dQZF1DWYUfsq4hxHWP"},{"collaborative":false,"description":"These country songs know exactly how you feel.","external_urls":{"spotify":"https:\/\/open.spotify.com\/playlist\/37i9dQZF1DXdmMcgFhLQ8u"},"href":"playlists\/37i9dQZF1DXdmMcgFhLQ8u","id":"37i9dQZF1DXdmMcgFhLQ8u","images":[{"height":null,"url":"https:\/\/i.scdn.co\/image\/ab67706f0000000387debe05df2a5723b4252b4f","width":null}],"name":"Country Heartache","owner":{"display_name":"Spotify","external_urls":{"spotify":"https:\/\/open.spotify.com\/user\/spotify"},"href":"users\/spotify","id":"spotify","type":"user","uri":"spotify:user:spotify"},"primary_color":null,"public":null,"snapshot_id":"MTYzMjA1MzU2MiwwMDAwMDAwMGQ0MWQ4Y2Q5OGYwMGIyMDRlOTgwMDk5OGVjZjg0Mjdl","tracks":{"href":"playlists\/37i9dQZF1DXdmMcgFhLQ8u\/tracks","total":75},"type":"playlist","uri":"spotify:playlist:37i9dQZF1DXdmMcgFhLQ8u"},{"collaborative":false,"description":"Current country music and artists making noise on Spotify. Featuring: Kolby Cooper","external_urls":{"spotify":"https:\/\/open.spotify.com\/playlist\/37i9dQZF1DX11Mx8sjx0nW"},"href":"playlists\/37i9dQZF1DX11Mx8sjx0nW","id":"37i9dQZF1DX11Mx8sjx0nW","images":[{"height":null,"url":"https:\/\/i.scdn.co\/image\/ab67706f000000030feaf644ad5b51458885a0dc","width":null}],"name":"RADAR Country","owner":{"display_name":"Spotify","external_urls":{"spotify":"https:\/\/open.spotify.com\/user\/spotify"},"href":"users\/spotify","id":"spotify","type":"user","uri":"spotify:user:spotify"},"primary_color":null,"public":null,"snapshot_id":"MTYzMDQ2ODgwMCwwMDAwMDM5YzAwMDAwMTdiOWY4MzdlOGQwMDAwMDE3YjllNjFlODFm","tracks":{"href":"playlists\/37i9dQZF1DX11Mx8sjx0nW\/tracks","total":50},"type":"playlist","uri":"spotify:playlist:37i9dQZF1DX11Mx8sjx0nW"},{"collaborative":false,"description":"The Women who put Country Music on the map.","external_urls":{"spotify":"https:\/\/open.spotify.com\/playlist\/37i9dQZF1DWSCp8Clax7tf"},"href":"playlists\/37i9dQZF1DWSCp8Clax7tf","id":"37i9dQZF1DWSCp8Clax7tf","images":[{"height":null,"url":"https:\/\/i.scdn.co\/image\/ab67706f000000038e45151be7abd95f8bf03c3d","width":null}],"name":"Legendary Women of Country","owner":{"display_name":"Spotify","external_urls":{"spotify":"https:\/\/open.spotify.com\/user\/spotify"},"href":"users\/spotify","id":"spotify","type":"user","uri":"spotify:user:spotify"},"primary_color":null,"public":null,"snapshot_id":"MTYxNTQyMjA2NSwwMDAwMDAwOTAwMDAwMTc4MWVhODhhNGMwMDAwMDE3MGFmNGE1OTgy","tracks":{"href":"playlists\/37i9dQZF1DWSCp8Clax7tf\/tracks","total":90},"type":"playlist","uri":"spotify:playlist:37i9dQZF1DWSCp8Clax7tf"},{"collaborative":false,"description":"Rock N' Roll Swagger Served Straight Up  \/ Cover: Whiskey Myers","external_urls":{"spotify":"https:\/\/open.spotify.com\/playlist\/37i9dQZF1DX7GqyyDpXu1q"},"href":"playlists\/37i9dQZF1DX7GqyyDpXu1q","id":"37i9dQZF1DX7GqyyDpXu1q","images":[{"height":null,"url":"https:\/\/i.scdn.co\/image\/ab67706f000000030c5b06df0dff97c617caee94","width":null}],"name":"Southern Comfort","owner":{"display_name":"Spotify","external_urls":{"spotify":"https:\/\/open.spotify.com\/user\/spotify"},"href":"users\/spotify","id":"spotify","type":"user","uri":"spotify:user:spotify"},"primary_color":null,"public":null,"snapshot_id":"MTYzMTkwNDg2MCwwMDAwMDNlMDAwMDAwMTdiZjUxYzA4YzMwMDAwMDE3MGFmNDM1ZWMz","tracks":{"href":"playlists\/37i9dQZF1DX7GqyyDpXu1q\/tracks","total":105},"type":"playlist","uri":"spotify:playlist:37i9dQZF1DX7GqyyDpXu1q"},{"collaborative":false,"description":"Classic cuts from the alternative country music scene. Cover: Uncle Tupelo","external_urls":{"spotify":"https:\/\/open.spotify.com\/playlist\/37i9dQZF1DWYBXdN7izJSV"},"href":"playlists\/37i9dQZF1DWYBXdN7izJSV","id":"37i9dQZF1DWYBXdN7izJSV","images":[{"height":null,"url":"https:\/\/i.scdn.co\/image\/ab67706f000000033ff4f674763ae5e58a06b01b","width":null}],"name":"Alt Country Classics","owner":{"display_name":"Spotify","external_urls":{"spotify":"https:\/\/open.spotify.com\/user\/spotify"},"href":"users\/spotify","id":"spotify","type":"user","uri":"spotify:user:spotify"},"primary_color":null,"public":null,"snapshot_id":"MTYwMjYwNDIxMSwwMDAwMDAwNTAwMDAwMTc1MjJhNzlkMDIwMDAwMDE3MGM0YzQ5MzVj","tracks":{"href":"playlists\/37i9dQZF1DWYBXdN7izJSV\/tracks","total":75},"type":"playlist","uri":"spotify:playlist:37i9dQZF1DWYBXdN7izJSV"},{"collaborative":false,"description":"Eagles, The Byrds and all your favorite country rock","external_urls":{"spotify":"https:\/\/open.spotify.com\/playlist\/37i9dQZF1DX4bf0P6HTTom"},"href":"playlists\/37i9dQZF1DX4bf0P6HTTom","id":"37i9dQZF1DX4bf0P6HTTom","images":[{"height":null,"url":"https:\/\/i.scdn.co\/image\/ab67706f0000000346edbf0e750d9bab7073d801","width":null}],"name":"Country Rock Classics","owner":{"display_name":"Spotify","external_urls":{"spotify":"https:\/\/open.spotify.com\/user\/spotify"},"href":"users\/spotify","id":"spotify","type":"user","uri":"spotify:user:spotify"},"primary_color":null,"public":null,"snapshot_id":"MTYzMjA1MzUxMCwwMDAwMDAwMGQ0MWQ4Y2Q5OGYwMGIyMDRlOTgwMDk5OGVjZjg0Mjdl","tracks":{"href":"playlists\/37i9dQZF1DX4bf0P6HTTom\/tracks","total":49},"type":"playlist","uri":"spotify:playlist:37i9dQZF1DX4bf0P6HTTom"},{"collaborative":false,"description":"The decade when country and rockabilly came together. Cover: Lefty Frizzell, Hank Williams, Kitty Wells","external_urls":{"spotify":"https:\/\/open.spotify.com\/playlist\/37i9dQZF1DWWnpcjfCqaW0"},"href":"playlists\/37i9dQZF1DWWnpcjfCqaW0","id":"37i9dQZF1DWWnpcjfCqaW0","images":[{"height":null,"url":"https:\/\/i.scdn.co\/image\/ab67706f000000030427215d945d0677fff40171","width":null}],"name":"50s Country","owner":{"display_name":"Spotify","external_urls":{"spotify":"https:\/\/open.spotify.com\/user\/spotify"},"href":"users\/spotify","id":"spotify","type":"user","uri":"spotify:user:spotify"},"primary_color":null,"public":null,"snapshot_id":"MTYzMjA1MzU0OCwwMDAwMDAwMGQ0MWQ4Y2Q5OGYwMGIyMDRlOTgwMDk5OGVjZjg0Mjdl","tracks":{"href":"playlists\/37i9dQZF1DWWnpcjfCqaW0\/tracks","total":96},"type":"playlist","uri":"spotify:playlist:37i9dQZF1DWWnpcjfCqaW0"},{"collaborative":false,"description":"Let these country tunes light up your day","external_urls":{"spotify":"https:\/\/open.spotify.com\/playlist\/37i9dQZF1DXdDIhtzn7T2e"},"href":"playlists\/37i9dQZF1DXdDIhtzn7T2e","id":"37i9dQZF1DXdDIhtzn7T2e","images":[{"height":null,"url":"https:\/\/i.scdn.co\/image\/ab67706f00000003f0048a2dc1fc325d6815840e","width":null}],"name":"Greener Pastures","owner":{"display_name":"Spotify","external_urls":{"spotify":"https:\/\/open.spotify.com\/user\/spotify"},"href":"users\/spotify","id":"spotify","type":"user","uri":"spotify:user:spotify"},"primary_color":null,"public":null,"snapshot_id":"MTYxODg5NDgwMCwwMDAwMDAwODAwMDAwMTc4ZWRhNjQ0Y2IwMDAwMDE3MGFmNGVhMTk3","tracks":{"href":"playlists\/37i9dQZF1DXdDIhtzn7T2e\/tracks","total":52},"type":"playlist","uri":"spotify:playlist:37i9dQZF1DXdDIhtzn7T2e"},{"collaborative":false,"description":"The Top Hot Country Tracks for 2020 in one playlist. Cover: Luke Combs","external_urls":{"spotify":"https:\/\/open.spotify.com\/playlist\/37i9dQZF1DWYvU2z6HruAo"},"href":"playlists\/37i9dQZF1DWYvU2z6HruAo","id":"37i9dQZF1DWYvU2z6HruAo","images":[{"height":null,"url":"https:\/\/i.scdn.co\/image\/ab67706f000000031290d00f33073b811c5e2860","width":null}],"name":"Hot Country Presents:  Best Country Songs of 2020","owner":{"display_name":"Spotify","external_urls":{"spotify":"https:\/\/open.spotify.com\/user\/spotify"},"href":"users\/spotify","id":"spotify","type":"user","uri":"spotify:user:spotify"},"primary_color":null,"public":null,"snapshot_id":"MTYwNjkyODU2NiwwMDAwMDAwNTAwMDAwMTc2MjQ2ODBhMDIwMDAwMDE3NjFjOWM4NGU4","tracks":{"href":"playlists\/37i9dQZF1DWYvU2z6HruAo\/tracks","total":62},"type":"playlist","uri":"spotify:playlist:37i9dQZF1DWYvU2z6HruAo"},{"collaborative":false,"description":"The decade of the Outlaws of Country Music - where traditional and crossover country collided.","external_urls":{"spotify":"https:\/\/open.spotify.com\/playlist\/37i9dQZF1DWYP5PUsVbso9"},"href":"playlists\/37i9dQZF1DWYP5PUsVbso9","id":"37i9dQZF1DWYP5PUsVbso9","images":[{"height":null,"url":"https:\/\/i.scdn.co\/image\/ab67706f00000003f5a7d861a5368f3220dcd670","width":null}],"name":"70s Country","owner":{"display_name":"Spotify","external_urls":{"spotify":"https:\/\/open.spotify.com\/user\/spotify"},"href":"users\/spotify","id":"spotify","type":"user","uri":"spotify:user:spotify"},"primary_color":null,"public":null,"snapshot_id":"MTYzMjA1MzUxNCwwMDAwMDAwMGQ0MWQ4Y2Q5OGYwMGIyMDRlOTgwMDk5OGVjZjg0Mjdl","tracks":{"href":"playlists\/37i9dQZF1DWYP5PUsVbso9\/tracks","total":96},"type":"playlist","uri":"spotify:playlist:37i9dQZF1DWYP5PUsVbso9"}],"limit":50,"next":"browse\/categories\/country\/playlists?country=US&offset=50&limit=50","offset":0,"previous":null,"total":84}}}